bridgeme/__init__.py
bridgeme/__main__.py
bridgeme/cli.py
bridgeme/exceptions.py
bridgeme/session.py
bridgeme/ssh_relay.py
bridgeme/terminal.py
bridgeme/utils.py
bridgeme-0.1.0.dist-info/licenses/LICENSE
bridgeme-0.1.0.dist-info/METADATA
bridgeme-0.1.0.dist-info/WHEEL
bridgeme-0.1.0.dist-info/entry_points.txt
bridgeme-0.1.0.dist-info/top_level.txt
bridgeme-0.1.0.dist-info/RECORD
