Metadata-Version: 2.4
Name: bridgeme
Version: 0.1.0
Summary: SSH relay-based reverse shell tool for IT troubleshooting
Home-page: https://github.com/yourusername/bridgeme
Author: Your Name
Author-email: Your Name <your.email@example.com>
Project-URL: Homepage, https://github.com/yourusername/bridgeme
Project-URL: Bug Reports, https://github.com/yourusername/bridgeme/issues
Project-URL: Source, https://github.com/yourusername/bridgeme
Classifier: Development Status :: 3 - Alpha
Classifier: Intended Audience :: System Administrators
Classifier: Topic :: System :: Systems Administration
Classifier: License :: OSI Approved :: MIT License
Classifier: Programming Language :: Python :: 3
Classifier: Programming Language :: Python :: 3.8
Classifier: Programming Language :: Python :: 3.9
Classifier: Programming Language :: Python :: 3.10
Classifier: Programming Language :: Python :: 3.11
Classifier: Operating System :: OS Independent
Requires-Python: >=3.8
License-File: LICENSE
Requires-Dist: paramiko>=2.7.0
Requires-Dist: click>=7.0
Requires-Dist: psutil>=5.0.0
Requires-Dist: colorama>=0.4.0
Provides-Extra: windows
Requires-Dist: pywinpty>=1.1.0; extra == "windows"
Provides-Extra: dev
Requires-Dist: pytest>=6.0; extra == "dev"
Requires-Dist: pytest-cov; extra == "dev"
Requires-Dist: black; extra == "dev"
Requires-Dist: flake8; extra == "dev"
Dynamic: author
Dynamic: home-page
Dynamic: license-file
Dynamic: requires-python
